twitter/__init__.py
twitter/ansi.py
twitter/api.py
twitter/archiver.py
twitter/auth.py
twitter/cmdline.py
twitter/follow.py
twitter/ircbot.py
twitter/logger.py
twitter/oauth.py
twitter/oauth2.py
twitter/oauth_dance.py
twitter/stream.py
twitter/stream_example.py
twitter/timezones.py
twitter/twitter_globals.py
twitter/util.py
twitter-1.19.6.dist-info/AUTHORS
twitter-1.19.6.dist-info/LICENSE
twitter-1.19.6.dist-info/METADATA
twitter-1.19.6.dist-info/WHEEL
twitter-1.19.6.dist-info/entry_points.txt
twitter-1.19.6.dist-info/top_level.txt
twitter-1.19.6.dist-info/zip-safe
twitter-1.19.6.dist-info/RECORD
